odoo8_addon_l10n_es_account_bank_statement_import_n43-8.0.4.0.3-py2.7-nspkg.pth
odoo8_addon_l10n_es_account_bank_statement_import_n43-8.0.4.0.3.dist-info/DESCRIPTION.rst
odoo8_addon_l10n_es_account_bank_statement_import_n43-8.0.4.0.3.dist-info/METADATA
odoo8_addon_l10n_es_account_bank_statement_import_n43-8.0.4.0.3.dist-info/RECORD
odoo8_addon_l10n_es_account_bank_statement_import_n43-8.0.4.0.3.dist-info/WHEEL
odoo8_addon_l10n_es_account_bank_statement_import_n43-8.0.4.0.3.dist-info/metadata.json
odoo8_addon_l10n_es_account_bank_statement_import_n43-8.0.4.0.3.dist-info/namespace_packages.txt
odoo8_addon_l10n_es_account_bank_statement_import_n43-8.0.4.0.3.dist-info/top_level.txt
odoo_addons/l10n_es_account_bank_statement_import_n43/README.rst
odoo_addons/l10n_es_account_bank_statement_import_n43/__init__.py
odoo_addons/l10n_es_account_bank_statement_import_n43/__openerp__.py
odoo_addons/l10n_es_account_bank_statement_import_n43/doc/norma_43_castellano.pdf
odoo_addons/l10n_es_account_bank_statement_import_n43/i18n/ca.po
odoo_addons/l10n_es_account_bank_statement_import_n43/i18n/ca_ES.po
odoo_addons/l10n_es_account_bank_statement_import_n43/i18n/cs.po
odoo_addons/l10n_es_account_bank_statement_import_n43/i18n/es.po
odoo_addons/l10n_es_account_bank_statement_import_n43/i18n/es_CR.po
odoo_addons/l10n_es_account_bank_statement_import_n43/i18n/fr.po
odoo_addons/l10n_es_account_bank_statement_import_n43/i18n/gl.po
odoo_addons/l10n_es_account_bank_statement_import_n43/i18n/hr.po
odoo_addons/l10n_es_account_bank_statement_import_n43/i18n/nl.po
odoo_addons/l10n_es_account_bank_statement_import_n43/i18n/pl.po
odoo_addons/l10n_es_account_bank_statement_import_n43/i18n/pt.po
odoo_addons/l10n_es_account_bank_statement_import_n43/i18n/pt_BR.po
odoo_addons/l10n_es_account_bank_statement_import_n43/i18n/ru.po
odoo_addons/l10n_es_account_bank_statement_import_n43/i18n/sl.po
odoo_addons/l10n_es_account_bank_statement_import_n43/i18n/sv.po
odoo_addons/l10n_es_account_bank_statement_import_n43/i18n/tr.po
odoo_addons/l10n_es_account_bank_statement_import_n43/i18n/vi.po
odoo_addons/l10n_es_account_bank_statement_import_n43/models/__init__.py
odoo_addons/l10n_es_account_bank_statement_import_n43/models/account_bank_statement_import_n43.py
odoo_addons/l10n_es_account_bank_statement_import_n43/models/account_journal.py
odoo_addons/l10n_es_account_bank_statement_import_n43/static/description/icon.png
odoo_addons/l10n_es_account_bank_statement_import_n43/static/description/icon_src.svg
odoo_addons/l10n_es_account_bank_statement_import_n43/tests/__init__.py
