Metadata-Version: 2.0
Name: odoo8-addon-l10n-es-account-bank-statement-import-n43
Version: 8.0.4.0.3
Summary: Importación de extractos bancarios españoles (Norma 43)
Home-page: https://github.com/OCA/l10n-spain
Author: Spanish Localization Team,Tecnativa,Antiun Ingenería S.L.,Odoo Community Association (OCA)
Author-email: support@odoo-community.org
License: AGPL-3
Platform: UNKNOWN
Classifier: Programming Language :: Python
Classifier: Framework :: Odoo
Classifier: License :: OSI Approved :: GNU Affero General Public License v3
Requires-Python: ~=2.7
Requires-Dist: odoo (<9.0a,>=8.0a)
Requires-Dist: odoo8-addon-account-bank-statement-import
